<plans xml:lang="de-CH">
    <person id="0">
        <plan>
            <act type="h" x="317253.061636729" y="5690927.71455574" end_time="08:00:00"/>
            <leg mode="car"/>
        </plan>
    </person>
    <person id="1">
        <plan>
            <act type="h" x="318154.903515915" y="5691514.15941979" end_time="08:00:00"/>
            <leg mode="car"/>
        </plan>
    </person>
    <person id="2">
        <plan>
            <act type="h" x="318243.395713732" y="5689259.99128695" end_time="08:00:00"/>
            <leg mode="car"/>
        </plan>
    </person>
    <person id="3">
        <plan>
            <act type="h" x="316757.454111734" y="5689801.17020498" end_time="08:00:00"/>
            <leg mode="car"/>
        </plan>
    </person>
    <person id="4">
        <plan>
            <act type="h" x="316076.453150089" y="5690665.50705074" end_time="08:00:00"/>
            <leg mode="car"/>
        </plan>
    </person>
    <person id="5">
        <plan>
            <act type="h" x="315615.147627193" y="5692139.19137423" end_time="08:00:00"/>
            <leg mode="car"/>
        </plan>
    </person>
    <person id="6">
        <plan>
            <act type="h" x="317346.61279805" y="5692337.76763989" end_time="08:00:00"/>
            <leg mode="car"/>
        </plan>
    </person>
    <person id="7">
        <plan>
            <act type="h" x="319605.335547518" y="5692951.45826787" end_time="08:00:00"/>
            <leg mode="car"/>
        </plan>
    </person>
    <person id="8">
        <plan>
            <act type="h" x="320993.543299989" y="5693054.89948234" end_time="08:00:00"/>
            <leg mode="car"/>
        </plan>
    </person>
    <person id="9">
        <plan>
            <act type="h" x="319589.126126076" y="5694018.52261042" end_time="08:00:00"/>
            <leg mode="car"/>
        </plan>
    </person>
    <person id="10">
        <plan>
            <act type="h" x="319721.685622609" y="5695702.4434431" end_time="08:00:00"/>
            <leg mode="car"/>
        </plan>
    </person>
    <person id="11">
        <plan>
            <act type="h" x="321632.773506238" y="5695637.45815061" end_time="08:00:00"/>
            <leg mode="car"/>
        </plan>
    </person>
    <person id="12">
        <plan>
            <act type="h" x="322931.41030928" y="5696640.35982168" end_time="08:00:00"/>
            <leg mode="car"/>
        </plan>
    </person>
    <person id="13">
        <plan>
            <act type="h" x="318993.914409979" y="5691240.08749539" end_time="08:00:00"/>
            <leg mode="car"/>
        </plan>
    </person>
    <person id="14">
        <plan>
            <act type="h" x="319897.58301006" y="5691321.48963042" end_time="08:00:00"/>
            <leg mode="car"/>
        </plan>
    </person>
    <person id="15">
        <plan>
            <act type="h" x="320326.940715924" y="5690208.95971978" end_time="08:00:00"/>
            <leg mode="car"/>
        </plan>
    </person>
    <person id="16">
        <plan>
            <act type="h" x="321398.464194304" y="5691338.77214204" end_time="08:00:00"/>
            <leg mode="car"/>
        </plan>
    </person>
    <person id="17">
        <plan>
            <act type="h" x="322978.6463699" y="5691974.57317441" end_time="08:00:00"/>
            <leg mode="car"/>
        </plan>
    </person>
    <person id="18">
        <plan>
            <act type="h" x="323791.084984878" y="5693023.35344509" end_time="08:00:00"/>
            <leg mode="car"/>
        </plan>
    </person>
    <person id="19">
        <plan>
            <act type="h" x="322408.84907782" y="5689463.39754569" end_time="08:00:00"/>
            <leg mode="car"/>
        </plan>
    </person>
    <person id="20">
        <plan>
            <act type="h" x="325071.397129587" y="5690775.37022464" end_time="08:00:00"/>
            <leg mode="car"/>
        </plan>
    </person>
    <person id="21">
        <plan>
            <act type="h" x="325010.86679895" y="5688731.17648985" end_time="08:00:00"/>
            <leg mode="car"/>
        </plan>
    </person>
    <person id="22">
        <plan>
            <act type="h" x="327266.654880267" y="5688789.27080699" end_time="08:00:00"/>
            <leg mode="car"/>
        </plan>
    </person>
    <person id="23">
        <plan>
            <act type="h" x="319148.266445888" y="5689757.46677043" end_time="08:00:00"/>
            <leg mode="car"/>
        </plan>
    </person>
    <person id="24">
        <plan>
            <act type="h" x="320544.867868263" y="5688415.37664728" end_time="08:00:00"/>
            <leg mode="car"/>
        </plan>
    </person>
    <person id="25">
        <plan>
            <act type="h" x="320492.876645491" y="5686837.35672" end_time="08:00:00"/>
            <leg mode="car"/>
        </plan>
    </person>
    <person id="26">
        <plan>
            <act type="h" x="321013.352988098" y="5685143.90896011" end_time="08:00:00"/>
            <leg mode="car"/>
        </plan>
    </person>
    <person id="27">
        <plan>
            <act type="h" x="323486.941979731" y="5683652.35235853" end_time="08:00:00"/>
            <leg mode="car"/>
        </plan>
    </person>
    <person id="28">
        <plan>
            <act type="h" x="323925.506433765" y="5686565.0985791" end_time="08:00:00"/>
            <leg mode="car"/>
        </plan>
    </person>
    <person id="29">
        <plan>
            <act type="h" x="316841.268254843" y="5688733.42086251" end_time="08:00:00"/>
            <leg mode="car"/>
        </plan>
    </person>
    <person id="30">
        <plan>
            <act type="h" x="316392.957929592" y="5687024.96315126" end_time="08:00:00"/>
            <leg mode="car"/>
        </plan>
    </person>
    <person id="31">
        <plan>
            <act type="h" x="318664.32492601" y="5687303.07714599" end_time="08:00:00"/>
            <leg mode="car"/>
        </plan>
    </person>
    <person id="32">
        <plan>
            <act type="h" x="318493.999858341" y="5686259.89844245" end_time="08:00:00"/>
            <leg mode="car"/>
        </plan>
    </person>
    <person id="33">
        <plan>
            <act type="h" x="318609.997660741" y="5685120.88596422" end_time="08:00:00"/>
            <leg mode="car"/>
        </plan>
    </person>
    <person id="34">
        <plan>
            <act type="h" x="315127.165194121" y="5688865.83364856" end_time="08:00:00"/>
            <leg mode="car"/>
        </plan>
    </person>
    <person id="35">
        <plan>
            <act type="h" x="314175.835987841" y="5689470.90007788" end_time="08:00:00"/>
            <leg mode="car"/>
        </plan>
    </person>
    <person id="36">
        <plan>
            <act type="h" x="313670.835535161" y="5688100.85914947" end_time="08:00:00"/>
            <leg mode="car"/>
        </plan>
    </person>
    <person id="37">
        <plan>
            <act type="h" x="312608.14146286" y="5685965.9017426" end_time="08:00:00"/>
            <leg mode="car"/>
        </plan>
    </person>
    <person id="38">
        <plan>
            <act type="h" x="312175.95183033" y="5684004.31785992" end_time="08:00:00"/>
            <leg mode="car"/>
        </plan>
    </person>
    <person id="39">
        <plan>
            <act type="h" x="310100.05681628" y="5682250.3355079" end_time="08:00:00"/>
            <leg mode="car"/>
        </plan>
    </person>
    <person id="40">
        <plan>
            <act type="h" x="311210.802583878" y="5689923.56690588" end_time="08:00:00"/>
            <leg mode="car"/>
        </plan>
    </person>
    <person id="41">
        <plan>
            <act type="h" x="311928.159376588" y="5688986.85751987" end_time="08:00:00"/>
            <leg mode="car"/>
        </plan>
    </person>
    <person id="42">
        <plan>
            <act type="h" x="311044.928617662" y="5688569.2684873" end_time="08:00:00"/>
            <leg mode="car"/>
        </plan>
    </person>
    <person id="43">
        <plan>
            <act type="h" x="310642.074286838" y="5688020.92214781" end_time="08:00:00"/>
            <leg mode="car"/>
        </plan>
    </person>
    <person id="44">
        <plan>
            <act type="h" x="309007.007064775" y="5687658.27442452" end_time="08:00:00"/>
            <leg mode="car"/>
        </plan>
    </person>
    <person id="45">
        <plan>
            <act type="h" x="309697.664153047" y="5689141.94606416" end_time="08:00:00"/>
            <leg mode="car"/>
        </plan>
    </person>
    <person id="46">
        <plan>
            <act type="h" x="308677.335884735" y="5689524.89625266" end_time="08:00:00"/>
            <leg mode="car"/>
        </plan>
    </person>
    <person id="47">
        <plan>
            <act type="h" x="314426.260441156" y="5690293.76694322" end_time="08:00:00"/>
            <leg mode="car"/>
        </plan>
    </person>
    <person id="48">
        <plan>
            <act type="h" x="314101.83326794" y="5691140.94735707" end_time="08:00:00"/>
            <leg mode="car"/>
        </plan>
    </person>
    <person id="49">
        <plan>
            <act type="h" x="312733.076557845" y="5690146.47862892" end_time="08:00:00"/>
            <leg mode="car"/>
        </plan>
    </person>
    <person id="50">
        <plan>
            <act type="h" x="313238.587489702" y="5692451.63354429" end_time="08:00:00"/>
            <leg mode="car"/>
        </plan>
    </person>
    <person id="51">
        <plan>
            <act type="h" x="310224.830016591" y="5693409.90124868" end_time="08:00:00"/>
            <leg mode="car"/>
        </plan>
    </person>
    <person id="52">
        <plan>
            <act type="h" x="309657.04713569" y="5691726.50975153" end_time="08:00:00"/>
            <leg mode="car"/>
        </plan>
    </person>
    <person id="53">
        <plan>
            <act type="h" x="315018.220173656" y="5694554.93499356" end_time="08:00:00"/>
            <leg mode="car"/>
        </plan>
    </person>
    <person id="54">
        <plan>
            <act type="h" x="312851.070022056" y="5694598.28596772" end_time="08:00:00"/>
            <leg mode="car"/>
        </plan>
    </person>
    <person id="55">
        <plan>
            <act type="h" x="311118.818025032" y="5697019.44737031" end_time="08:00:00"/>
            <leg mode="car"/>
        </plan>
    </person>
    <person id="56">
        <plan>
            <act type="h" x="314495.216820176" y="5697806.75484074" end_time="08:00:00"/>
            <leg mode="car"/>
        </plan>
    </person>
    <person id="57">
        <plan>
            <act type="h" x="316269.721117532" y="5693239.60315434" end_time="08:00:00"/>
            <leg mode="car"/>
        </plan>
    </person>
    <person id="58">
        <plan>
            <act type="h" x="316962.510340736" y="5694024.86422139" end_time="08:00:00"/>
            <leg mode="car"/>
        </plan>
    </person>
    <person id="59">
        <plan>
            <act type="h" x="316881.868521552" y="5695065.21092575" end_time="08:00:00"/>
            <leg mode="car"/>
        </plan>
    </person>
    <person id="60">
        <plan>
            <act type="h" x="318227.961550617" y="5694416.77505061" end_time="08:00:00"/>
            <leg mode="car"/>
        </plan>
    </person>
    <person id="61">
        <plan>
            <act type="h" x="321859.915280564" y="5699665.84318731" end_time="08:00:00"/>
            <leg mode="car"/>
        </plan>
    </person>
    <person id="62">
        <plan>
            <act type="h" x="317368.468146507" y="5697877.53083895" end_time="08:00:00"/>
            <leg mode="car"/>
        </plan>
    </person>
</plans>